django_gavaconnect-0.1.0.dist-info/licenses/LICENSE
gavaconnect/__init__.py
gavaconnect/api.py
gavaconnect/apps.py
gavaconnect/auth.py
gavaconnect/conf.py
gavaconnect/exceptions.py
gavaconnect/http.py
gavaconnect/typing.py
gavaconnect/management/__init__.py
gavaconnect/management/commands/__init__.py
gavaconnect/management/commands/gavaconnect_selftest.py
django_gavaconnect-0.1.0.dist-info/METADATA
django_gavaconnect-0.1.0.dist-info/WHEEL
django_gavaconnect-0.1.0.dist-info/top_level.txt
django_gavaconnect-0.1.0.dist-info/RECORD
