Metadata-Version: 2.4
Name: django-gavaconnect
Version: 0.1.0
Summary: Reusable Django app to call KRA GavaConnect APIs (sandbox & production).
Author-email: Brian Nganga <briannganga70@gmail.com>
License: MIT
Project-URL: Homepage, https://github.com/mworia-Br/django-gavaconnect
Requires-Python: >=3.9
License-File: LICENSE
Requires-Dist: Django>=3.2
Requires-Dist: requests>=2.31
Dynamic: license-file
